vibe_ocr/__init__.py
vibe_ocr/game_actions.py
vibe_ocr/ocr_helper.py
vibe_ocr-0.1.6.dist-info/METADATA
vibe_ocr-0.1.6.dist-info/WHEEL
vibe_ocr-0.1.6.dist-info/RECORD
