Metadata-Version: 2.4
Name: vibe-ocr
Version: 0.1.6
Summary: A decoupled OCR helper library using PaddleOCR (via remote server) and SQLite caching.
Project-URL: Homepage, https://github.com/jasoft/pythonlib
Project-URL: Bug Tracker, https://github.com/jasoft/pythonlib/issues
Author-email: Johnny Wang <ja.invent@gmail.com>
Classifier: License :: OSI Approved :: MIT License
Classifier: Operating System :: OS Independent
Classifier: Programming Language :: Python :: 3
Requires-Python: >=3.7
Requires-Dist: imagehash
Requires-Dist: numpy
Requires-Dist: opencv-python
Requires-Dist: pillow
Requires-Dist: python-dotenv
Requires-Dist: requests
